jazal/__init__.py
jazal/missing_path_arg_warner.py
jazal/path_checker.py
jazal/path_util.py
jazal/reactive_path_checker.py
tests/__init__.py
tests/missing_path_arg_warner_tests.py
tests/path_checker_tests.py
tests/path_util_tests.py
tests/reactive_path_checker_tests.py
tests/run_all_tests.py
jazal-2.0.0.dist-info/LICENSE
jazal-2.0.0.dist-info/METADATA
jazal-2.0.0.dist-info/WHEEL
jazal-2.0.0.dist-info/top_level.txt
jazal-2.0.0.dist-info/RECORD
