Metadata-Version: 2.1
Name: jazal
Version: 2.0.0
Summary: Jazal performs certain verifications on filepaths before a function or a script uses them.
Home-page: https://github.com/GRV96/jazal
Author: Guyllaume Rousseau
License: MIT
Platform: UNKNOWN
Classifier: Development Status :: 5 - Production/Stable
Classifier: Intended Audience :: Developers
Classifier: License :: OSI Approved :: MIT License
Classifier: Operating System :: OS Independent
Classifier: Programming Language :: Python :: 3
Classifier: Topic :: Software Development :: Libraries :: Python Modules
Classifier: Topic :: Utilities
License-File: LICENSE
